dialog_whatsapp/__init__.py
dialog_whatsapp/plugin.py
dialog_whatsapp/responses.py
dialog_whatsapp/settings.py
dialog_whatsapp-0.0.1.7.dist-info/METADATA
dialog_whatsapp-0.0.1.7.dist-info/WHEEL
dialog_whatsapp-0.0.1.7.dist-info/entry_points.txt
dialog_whatsapp-0.0.1.7.dist-info/RECORD
