Metadata-Version: 2.1
Name: dialog-whatsapp
Version: 0.0.1.7
Summary: 
Author: Vinicius Mesel
Author-email: 4984147+vmesel@users.noreply.github.com
Requires-Python: >=3.11,<3.13
Classifier: Programming Language :: Python :: 3
Classifier: Programming Language :: Python :: 3.11
Classifier: Programming Language :: Python :: 3.12
Requires-Dist: dialog-lib (>=0.0.1.3,<0.0.2.0)
